i18n/__init__.py
i18n/base.py
i18n/cli.py
i18n/config.py
i18n/errors.py
i18n/parser.py
pylemoni18n-0.0.1.dist-info/entry_points.txt
pylemoni18n-0.0.1.dist-info/LICENSE
pylemoni18n-0.0.1.dist-info/WHEEL
pylemoni18n-0.0.1.dist-info/METADATA
pylemoni18n-0.0.1.dist-info/RECORD
